LICENSE
README.md
setup.py
dicom_to_cnn/__init__.py
dicom_to_cnn.egg-info/PKG-INFO
dicom_to_cnn.egg-info/SOURCES.txt
dicom_to_cnn.egg-info/dependency_links.txt
dicom_to_cnn.egg-info/requires.txt
dicom_to_cnn.egg-info/top_level.txt
dicom_to_cnn/enums/SopClassUID.py
dicom_to_cnn/enums/TagEnum.py
dicom_to_cnn/enums/__init__.py
dicom_to_cnn/model/__init__.py
dicom_to_cnn/model/fusion/Fusion.py
dicom_to_cnn/model/fusion/__init__.py
dicom_to_cnn/model/petctviewer/CsvReader.py
dicom_to_cnn/model/petctviewer/MaskBuilder.py
dicom_to_cnn/model/petctviewer/Roi.py
dicom_to_cnn/model/petctviewer/RoiElipse.py
dicom_to_cnn/model/petctviewer/RoiFactory.py
dicom_to_cnn/model/petctviewer/RoiNifti.py
dicom_to_cnn/model/petctviewer/RoiPolygon.py
dicom_to_cnn/model/petctviewer/__init__.py
dicom_to_cnn/model/petctviewer/csv_volume.py
dicom_to_cnn/model/post_processing/__init__.py
dicom_to_cnn/model/post_processing/clustering/Watershed.py
dicom_to_cnn/model/post_processing/clustering/__init__.py
dicom_to_cnn/model/post_processing/mip/MIP_Generator.py
dicom_to_cnn/model/post_processing/mip/__init__.py
dicom_to_cnn/model/reader/Instance.py
dicom_to_cnn/model/reader/Instance_RTDose.py
dicom_to_cnn/model/reader/Instance_RTSS.py
dicom_to_cnn/model/reader/Nifti.py
dicom_to_cnn/model/reader/Series.py
dicom_to_cnn/model/reader/SeriesCT.py
dicom_to_cnn/model/reader/SeriesPT.py
dicom_to_cnn/model/reader/__init__.py
dicom_to_cnn/model/segmentation/Abstract_Writer.py
dicom_to_cnn/model/segmentation/ExportSegmentation_Writer.py
dicom_to_cnn/model/segmentation/MaskBuilder_DICOMSEG.py
dicom_to_cnn/model/segmentation/MaskBuilder_RTSS.py
dicom_to_cnn/model/segmentation/__init__.py
dicom_to_cnn/model/segmentation/dicom_seg/DICOMSEG_Writer.py
dicom_to_cnn/model/segmentation/dicom_seg/__init__.py
dicom_to_cnn/model/segmentation/nifti/Nifti_Writer.py
dicom_to_cnn/model/segmentation/nifti/__init__.py
dicom_to_cnn/model/segmentation/rtstruct/ROIContourSequence.py
dicom_to_cnn/model/segmentation/rtstruct/RTROIObservationsSequence.py
dicom_to_cnn/model/segmentation/rtstruct/RTSS_Writer.py
dicom_to_cnn/model/segmentation/rtstruct/ReferencedFrameOfReferenceSequence.py
