Metadata-Version: 2.1
Name: dicom-to-cnn
Version: 0.74
Summary: Python Library to handle Input / Output conversion in Dicom <=> Convolutional Neural Network 
Home-page: https://github.com/wendyrvllr/Dicom-To-CNN
Author: 
License: UNKNOWN
Download-URL: https://github.com/wendyrvllr/Dicom-To-CNN/archive/refs/tags/74.tar.gz
Platform: UNKNOWN
Classifier: Programming Language :: Python :: 3.7
Classifier: Programming Language :: Python :: 3.8
Classifier: License :: OSI Approved :: MIT License
Classifier: Operating System :: OS Independent
Requires-Python: >=3.7
License-File: LICENSE
